[
  {
    "Eden Hazard": [
      "Chelsea",
      "6",
      "Belgium",
      "https://upload.wikimedia.org/wikipedia/commons/thumb/9/92/Flag_of_Belgium_%28civil%29.svg/23px-Flag_of_Belgium_%28civil%29.svg.png"
    ],
    "Sergio Ag\u00fcero": [
      "Manchester City",
      "5",
      "Argentina",
      "https://upload.wikimedia.org/wikipedia/commons/thumb/1/1a/Flag_of_Argentina.svg/23px-Flag_of_Argentina.svg.png"
    ],
    "Harry Kane": [
      "Tottenham Hotspur",
      5,
      "England",
      "https://upload.wikimedia.org/wikipedia/en/thumb/b/be/Flag_of_England.svg/23px-Flag_of_England.svg.png"
    ],
    "Aleksandar Mitrovi\u0107": [
      "Fulham",
      5,
      "Serbia",
      "https://upload.wikimedia.org/wikipedia/commons/thumb/f/ff/Flag_of_Serbia.svg/23px-Flag_of_Serbia.svg.png"
    ],
    "Marko Arnautovi\u0107": [
      "West Ham United",
      "4",
      "Austria",
      "https://upload.wikimedia.org/wikipedia/commons/thumb/4/41/Flag_of_Austria.svg/23px-Flag_of_Austria.svg.png"
    ],
    "Romelu Lukaku": [
      "Manchester United",
      4,
      "Belgium",
      "https://upload.wikimedia.org/wikipedia/commons/thumb/9/92/Flag_of_Belgium_%28civil%29.svg/23px-Flag_of_Belgium_%28civil%29.svg.png"
    ],
    "Sadio Man\u00e9": [
      "Liverpool",
      4,
      "Senegal",
      "https://upload.wikimedia.org/wikipedia/commons/thumb/f/fd/Flag_of_Senegal.svg/23px-Flag_of_Senegal.svg.png"
    ],
    "Glenn Murray": [
      "Brighton and Hove Albion",
      4,
      "England",
      "https://upload.wikimedia.org/wikipedia/en/thumb/b/be/Flag_of_England.svg/23px-Flag_of_England.svg.png"
    ],
    "Raheem Sterling": [
      "Manchester City",
      4,
      "England",
      "https://upload.wikimedia.org/wikipedia/en/thumb/b/be/Flag_of_England.svg/23px-Flag_of_England.svg.png"
    ],
    "Ryan Fraser": [
      "Bournemouth",
      "3",
      "Scotland",
      "https://upload.wikimedia.org/wikipedia/commons/thumb/1/10/Flag_of_Scotland.svg/23px-Flag_of_Scotland.svg.png"
    ],
    "Andre Gray": [
      "Watford",
      3,
      "England",
      "https://upload.wikimedia.org/wikipedia/en/thumb/b/be/Flag_of_England.svg/23px-Flag_of_England.svg.png"
    ],
    "Danny Ings": [
      "Southampton",
      3,
      "England",
      "https://upload.wikimedia.org/wikipedia/en/thumb/b/be/Flag_of_England.svg/23px-Flag_of_England.svg.png"
    ],
    "James Maddison": [
      "Leicester City",
      3,
      "England",
      "https://upload.wikimedia.org/wikipedia/en/thumb/b/be/Flag_of_England.svg/23px-Flag_of_England.svg.png"
    ],
    "Lucas Moura": [
      "Tottenham Hotspur",
      3,
      "Brazil",
      "https://upload.wikimedia.org/wikipedia/en/thumb/0/05/Flag_of_Brazil.svg/22px-Flag_of_Brazil.svg.png"
    ],
    "Pedro": [
      "Chelsea",
      3,
      "Spain",
      "https://upload.wikimedia.org/wikipedia/en/thumb/9/9a/Flag_of_Spain.svg/23px-Flag_of_Spain.svg.png"
    ],
    "Roberto Pereyra": [
      "Watford",
      3,
      "Argentina",
      "https://upload.wikimedia.org/wikipedia/commons/thumb/1/1a/Flag_of_Argentina.svg/23px-Flag_of_Argentina.svg.png"
    ],
    "Richarlison": [
      "Everton",
      3,
      "Brazil",
      "https://upload.wikimedia.org/wikipedia/en/thumb/0/05/Flag_of_Brazil.svg/22px-Flag_of_Brazil.svg.png"
    ],
    "Mohamed Salah": [
      "Liverpool",
      3,
      "Egypt",
      "https://upload.wikimedia.org/wikipedia/commons/thumb/f/fe/Flag_of_Egypt.svg/23px-Flag_of_Egypt.svg.png"
    ],
    "Gylfi Sigur\u00f0sson": [
      "Everton",
      3,
      "Iceland",
      "https://upload.wikimedia.org/wikipedia/commons/thumb/c/ce/Flag_of_Iceland.svg/21px-Flag_of_Iceland.svg.png"
    ],
    "Jamie Vardy": [
      "Leicester City",
      3,
      "England",
      "https://upload.wikimedia.org/wikipedia/en/thumb/b/be/Flag_of_England.svg/23px-Flag_of_England.svg.png"
    ],
    "Wilfried Zaha": [
      "Crystal Palace",
      3,
      "Ivory Coast",
      "https://upload.wikimedia.org/wikipedia/commons/thumb/f/fe/Flag_of_C%C3%B4te_d%27Ivoire.svg/23px-Flag_of_C%C3%B4te_d%27Ivoire.svg.png"
    ]
  },
  {
    "Jos\u00e9 Holebas": [
      "Watford",
      "4",
      "Greece",
      "https://upload.wikimedia.org/wikipedia/commons/thumb/5/5c/Flag_of_Greece.svg/23px-Flag_of_Greece.svg.png"
    ],
    "Benjamin Mendy": [
      "Manchester City",
      4,
      "France",
      "https://upload.wikimedia.org/wikipedia/en/thumb/c/c3/Flag_of_France.svg/23px-Flag_of_France.svg.png"
    ],
    "Olivier Giroud": [
      "Chelsea",
      "3",
      "France",
      "https://upload.wikimedia.org/wikipedia/en/thumb/c/c3/Flag_of_France.svg/23px-Flag_of_France.svg.png"
    ],
    "J\u00f3hann Berg Gu\u00f0mundsson": [
      "Burnley",
      3,
      "Iceland",
      "https://upload.wikimedia.org/wikipedia/commons/thumb/c/ce/Flag_of_Iceland.svg/21px-Flag_of_Iceland.svg.png"
    ],
    "Anthony Knockaert": [
      "Brighton and Hove Albion",
      3,
      "France",
      "https://upload.wikimedia.org/wikipedia/en/thumb/c/c3/Flag_of_France.svg/23px-Flag_of_France.svg.png"
    ],
    "Luciano Vietto": [
      "Fulham",
      3,
      "Argentina",
      "https://upload.wikimedia.org/wikipedia/commons/thumb/1/1a/Flag_of_Argentina.svg/23px-Flag_of_Argentina.svg.png"
    ],
    "Callum Wilson": [
      "Bournemouth",
      3,
      "England",
      "https://upload.wikimedia.org/wikipedia/en/thumb/b/be/Flag_of_England.svg/23px-Flag_of_England.svg.png"
    ]
  }
]